python_play/__init__.py
python_play/__main__.py
python_play/__version__.py
python_play/player.py
python_play/viewer.py
python_play-1.0.5.dist-info/LICENSE.md
python_play-1.0.5.dist-info/METADATA
python_play-1.0.5.dist-info/WHEEL
python_play-1.0.5.dist-info/top_level.txt
python_play-1.0.5.dist-info/RECORD
