Metadata-Version: 2.1
Name: python-play
Version: 1.0.5
Summary: play mp3 audio files
Home-page: https://github.com/adisakshya/python_play
Author: Adisakshya Chauhan
Author-email: adisakshya98@gmail.com
License: MIT
Platform: UNKNOWN
Classifier: License :: OSI Approved :: MIT License
Classifier: Programming Language :: Python
Classifier: Programming Language :: Python :: 3
Classifier: Programming Language :: Python :: 3.6
Classifier: Programming Language :: Python :: 3.7
Requires-Python: >=3.6.0
